Metadata-Version: 1.2
Name: FoxHustleQR
Version: 1.0.2
Summary: QR-code Generator
Home-page: https://github.com/Fox-Hustle/QR-generator.git
Author: welcome32
Author-email: welcome32@foxhustle.ru
License: MIT
Platform: UNKNOWN
Requires-Python: >=3.6
